[
    {
      "pack_code": "TDoM",
      "pack_name": "The Dark of Mirkwood",
      "type_code": "treasure",
      "type_name": "Campaign",
      "sphere_code": "neutral",
      "sphere_name": "Neutral",
      "position": 41,
      "code": "41041",
      "name": "Stalking Goblin",
      "traits": "Goblin. Orc.",
      "text": "<b>Forced:</b> After Stalking Goblin engages you, search the encounter deck, discard pile, and your collection (in that order) for a Goblin Sniper and add it to the staging area. Shuffle the encounter deck.\r\n<i><b>Shadow:</b> Add Stalking Goblin to the staging area.</i>",
      "is_unique": false,
      "willpower": 2,
      "attack": 2,
      "defense": 2,
      "health": 2,
      "quantity": 1,
      "deck_limit": 1,
      "illustrator": "JB Casacop",
      "octgnid": "f720a770-0164-42c8-83c7-773366729449",
      "has_errata": false,
      "url": "https://ringsdb.com/card/41041",
      "imagesrc": "/bundles/cards/41041.png"
    },
    {
      "pack_code": "TDoM",
      "pack_name": "The Dark of Mirkwood",
      "type_code": "treasure",
      "type_name": "Campaign",
      "sphere_code": "neutral",
      "sphere_name": "Neutral",
      "position": 42,
      "code": "41042",
      "name": "Shiny Distraction",
      "traits": "Treasure.",
      "text": "Surge. Doomed 1.\r\n<b>When Revealed:</b> Each player may add 1 resource to each of their heroes' pools. Each player that does raises their threat by 5.",
      "is_unique": false,
      "quantity": 1,
      "deck_limit": 1,
      "illustrator": "Andreas Zafiratos",
      "octgnid": "4751b29d-9860-4079-8dde-55a94a493ba7",
      "has_errata": false,
      "url": "https://ringsdb.com/card/41042",
      "imagesrc": "/bundles/cards/41042.png"
    },
    {
      "pack_code": "TDoM",
      "pack_name": "The Dark of Mirkwood",
      "type_code": "treasure",
      "type_name": "Campaign",
      "sphere_code": "neutral",
      "sphere_name": "Neutral",
      "position": 43,
      "code": "41043",
      "name": "Guilty Conscience",
      "text": "Surge.\r\n<b>When Revealed:</b> Attach to the hero with the highest threat cost. (Counts as an <i><b>Adaptation</b></i> attachment with the text: \"<b>Forced:</b> Raise your threat by 2 at the end of each round. <b>Action:</b> Spend 2 resources from attached hero's pool to discard this card.\")",
      "is_unique": false,
      "quantity": 1,
      "deck_limit": 1,
      "illustrator": "Lin Hsiang",
      "octgnid": "62c595a8-8f6c-4541-848b-32823ec21075",
      "has_errata": false,
      "url": "https://ringsdb.com/card/41043",
      "imagesrc": "/bundles/cards/41043.png"
    },
    {
      "pack_code": "TDoM",
      "pack_name": "The Dark of Mirkwood",
      "type_code": "treasure",
      "type_name": "Campaign",
      "sphere_code": "neutral",
      "sphere_name": "Neutral",
      "position": 44,
      "code": "41044",
      "name": "The Fervor of Lore",
      "traits": "Adaptation.",
      "text": "Setup. Attach to a hero.\r\nAttached hero gains the [lore] resource icon.\r\n<b>Action:</b> Choose and discard 3 cards from your hand to heal all damage from a hero. (Limit once per campaign. Record in Campaign Log when used.)",
      "is_unique": false,
      "cost": "0",
      "quantity": 1,
      "deck_limit": 1,
      "illustrator": "Drazenka Kimpel",
      "octgnid": "a7ba36ce-d818-4df0-8543-bcd02e1fd8f1",
      "has_errata": false,
      "url": "https://ringsdb.com/card/41044",
      "imagesrc": "/bundles/cards/41044.png"
    },
    {
      "pack_code": "TDoM",
      "pack_name": "The Dark of Mirkwood",
      "type_code": "treasure",
      "type_name": "Campaign",
      "sphere_code": "neutral",
      "sphere_name": "Neutral",
      "position": 45,
      "code": "41045",
      "name": "The Might of Tactics",
      "traits": "Adaptation.",
      "text": "Setup. Attach to a hero.\r\nAttached hero gains the [tactics] resource icon.\r\n<b>Action:</b> Deal 1 damage to the attached hero to deal 3 damage to an enemy engaged with you. (Limit once per campaign. Record in Campaign Log when used.)",
      "is_unique": false,
      "cost": "0",
      "quantity": 1,
      "deck_limit": 1,
      "illustrator": "JB Casacop",
      "octgnid": "1fbb29c8-d42e-4767-9a63-0bcbdd167782",
      "has_errata": false,
      "url": "https://ringsdb.com/card/41045",
      "imagesrc": "/bundles/cards/41045.png"
    },
    {
      "pack_code": "TDoM",
      "pack_name": "The Dark of Mirkwood",
      "type_code": "treasure",
      "type_name": "Campaign",
      "sphere_code": "neutral",
      "sphere_name": "Neutral",
      "position": 46,
      "code": "41046",
      "name": "The Power of Spirit",
      "traits": "Adaptation.",
      "text": "Setup. Attach to a hero.\r\nAttached hero gains the [spirit] resource icon.\r\n<b>Action:</b> Exhaust the attached hero to place 3 progress on a location. (Limit once per campaign. Record in Campaign Log when used.)",
      "is_unique": false,
      "cost": "0",
      "quantity": 1,
      "deck_limit": 1,
      "illustrator": "Drazenka Kimpel",
      "octgnid": "6946e419-efbf-4a0b-93ac-4e181ebe1394",
      "has_errata": false,
      "url": "https://ringsdb.com/card/41046",
      "imagesrc": "/bundles/cards/41046.png"
    },
    {
      "pack_code": "TDoM",
      "pack_name": "The Dark of Mirkwood",
      "type_code": "treasure",
      "type_name": "Campaign",
      "sphere_code": "neutral",
      "sphere_name": "Neutral",
      "position": 47,
      "code": "41047",
      "name": "The Secret of Leadership",
      "traits": "Adaptation.",
      "text": "Setup. Attach to a hero.\r\nAttached hero gains the [leadership] resource icon.\r\n<b>Action:</b> Spend 1 resource from the attached hero's resource pool to ready a hero. (Limit once per campaign. Record in Campaign Log when used.)",
      "is_unique": false,
      "cost": "0",
      "quantity": 1,
      "deck_limit": 1,
      "illustrator": "Borja Pindado",
      "octgnid": "0d6f4f57-d276-4bef-a637-a21d0b648aa8",
      "has_errata": false,
      "url": "https://ringsdb.com/card/41047",
      "imagesrc": "/bundles/cards/41047.png"
    },
    {
      "pack_code": "TDoM",
      "pack_name": "The Dark of Mirkwood",
      "type_code": "treasure",
      "type_name": "Campaign",
      "sphere_code": "neutral",
      "sphere_name": "Neutral",
      "position": 48,
      "code": "41048",
      "name": "\"No Time to Waste!\"",
      "text": "When playing this card, choose one:\r\n<b>Quest Action:</b> Remove \"No Time to Waste!\" from the game and from the Campaign Pool to reduce each player's threat by 3. Reveal the top card of the encounter deck.\r\n<b>Quest Action:</b> Draw 1 card.",
      "is_unique": false,
      "cost": "0",
      "quantity": 4,
      "deck_limit": 1,
      "illustrator": "Borja Pindado",
      "octgnid": "be386168-0447-409c-abd6-cedda5e16cd2",
      "has_errata": false,
      "url": "https://ringsdb.com/card/41048",
      "imagesrc": "/bundles/cards/41048.png"
    },
    {
      "pack_code": "TDoM",
      "pack_name": "The Dark of Mirkwood",
      "type_code": "treasure",
      "type_name": "Campaign",
      "sphere_code": "neutral",
      "sphere_name": "Neutral",
      "position": 49,
      "code": "41049",
      "name": "Ranger Sense",
      "text": "When playing this card, choose one:\r\n<b>Action:</b> Remove Ranger Sense from the game and from the Campaign Pooll to look at the top 4 cards of your deck. Add 1 to your hand and put the rest back in any order.\r\n<b>Action:</b> Draw 1 card.",
      "is_unique": false,
      "cost": "0",
      "quantity": 4,
      "deck_limit": 1,
      "illustrator": "Andreas Zafiratos",
      "octgnid": "f470ab0f-e089-4921-ac2d-45e5d70ed8c0",
      "has_errata": false,
      "url": "https://ringsdb.com/card/41049",
      "imagesrc": "/bundles/cards/41049.png"
    }
  ]
  